{"sourceName":"@Blizzard_APIDocumentation\\SystemsAPIMixin.lua","lineDefined":0,"lastLineDefined":0,"upvalueCount":0,"paramCount":0,"is_vararg":2,"maxStackSize":3,"instructions":[5,0,1,0,5,1,2,0,28,0,2,2,7,0,0,0,5,0,0,0,36,1,0,0,9,0,259,1,5,0,0,0,36,1,1,0,9,0,260,1,5,0,0,0,36,1,2,0,9,0,261,1,5,0,0,0,36,1,3,0,9,0,262,1,5,0,0,0,36,1,4,0,9,0,263,1,5,0,0,0,36,1,5,0,9,0,264,1,5,0,0,0,36,1,6,0,9,0,265,1,5,0,0,0,36,1,7,0,9,0,266,1,5,0,0,0,36,1,8,0,9,0,267,1,5,0,0,0,36,1,9,0,9,0,268,1,36,0,10,0,5,1,0,0,36,2,11,0,0,0,0,0,9,1,269,2,5,1,0,0,36,2,12,0,9,1,270,2,5,1,0,0,36,2,13,0,9,1,271,2,5,1,0,0,36,2,14,0,9,1,272,2,30,0,1,0],"constants":["SystemsAPIMixin","CreateFromMixins","BaseAPIMixin","GetType","GetLinkHexColor","GetNamespaceName","GetLoweredNamespaceName","MatchesSearchString","GetSingleOutputLine","GetDetailedOutputLines","MatchesName","MatchesNameCaseInsenstive","FindAllAPIMatches","ListAllAPI","GetNumTables","GetNumFunctions","GetNumEvents"],"functions":[{"sourceName":"","lineDefined":3,"lastLineDefined":5,"upvalueCount":0,"paramCount":1,"is_vararg":0,"maxStackSize":2,"instructions":[1,1,0,0,30,1,2,0,30,0,1,0],"constants":["system"],"functions":[],"linePositions":[4,4,5],"locals":[{"varname":"self","startpc":0,"endpc":2}],"upvalues":[]},{"sourceName":"","lineDefined":7,"lastLineDefined":9,"upvalueCount":0,"paramCount":1,"is_vararg":0,"maxStackSize":2,"instructions":[1,1,0,0,30,1,2,0,30,0,1,0],"constants":["ff55dd"],"functions":[],"linePositions":[8,8,9],"locals":[{"varname":"self","startpc":0,"endpc":2}],"upvalues":[]},{"sourceName":"","lineDefined":11,"lastLineDefined":13,"upvalueCount":0,"paramCount":1,"is_vararg":0,"maxStackSize":2,"instructions":[6,1,0,256,26,1,0,1,22,0,1,0,1,1,1,0,30,1,2,0,30,0,1,0],"constants":["Namespace",""],"functions":[],"linePositions":[12,12,12,12,12,13],"locals":[{"varname":"self","startpc":0,"endpc":5}],"upvalues":[]},{"sourceName":"","lineDefined":15,"lastLineDefined":20,"upvalueCount":0,"paramCount":1,"is_vararg":0,"maxStackSize":3,"instructions":[6,1,0,256,26,1,0,1,22,0,5,0,11,1,0,257,28,1,2,2,11,1,1,258,28,1,2,2,9,0,256,1,6,1,0,256,30,1,2,0,30,0,1,0],"constants":["loweredNamespaceName","GetNamespaceName","lower"],"functions":[],"linePositions":[16,16,16,17,17,17,17,17,19,19,20],"locals":[{"varname":"self","startpc":0,"endpc":10}],"upvalues":[]},{"sourceName":"","lineDefined":22,"lastLineDefined":32,"upvalueCount":0,"paramCount":2,"is_vararg":0,"maxStackSize":5,"instructions":[11,2,0,256,28,2,2,2,11,2,2,257,0,4,1,0,28,2,3,2,26,2,0,0,22,0,2,0,2,2,1,0,30,2,2,0,11,2,0,258,0,4,1,0,28,2,3,2,26,2,0,0,22,0,2,0,2,2,1,0,30,2,2,0,2,2,0,0,30,2,2,0,30,0,1,0],"constants":["GetLoweredName","match","MatchesAnyDocumentation"],"functions":[],"linePositions":[23,23,23,23,23,23,23,24,24,27,27,27,27,27,28,28,31,31,32],"locals":[{"varname":"self","startpc":0,"endpc":18},{"varname":"searchString","startpc":0,"endpc":18}],"upvalues":[]},{"sourceName":"","lineDefined":34,"lastLineDefined":39,"upvalueCount":0,"paramCount":1,"is_vararg":0,"maxStackSize":6,"instructions":[6,1,0,256,26,1,0,0,22,0,9,0,1,1,1,0,11,1,1,258,11,3,0,259,28,3,2,2,11,4,0,260,28,4,2,2,6,5,0,256,29,1,5,0,30,1,0,0,5,1,5,0,6,1,1,262,0,2,0,0,29,1,2,0,30,1,0,0,30,0,1,0],"constants":["Namespace","%s %s (%s)","format","GetPrettyType","GenerateAPILink","BaseAPIMixin","GetSingleOutputLine"],"functions":[],"linePositions":[35,35,35,36,36,36,36,36,36,36,36,36,38,38,38,38,38,39],"locals":[{"varname":"self","startpc":0,"endpc":17}],"upvalues":[]},{"sourceName":"","lineDefined":41,"lastLineDefined":69,"upvalueCount":0,"paramCount":1,"is_vararg":0,"maxStackSize":12,"instructions":[10,1,0,0,5,2,0,0,6,2,2,257,0,3,1,0,11,4,0,258,28,4,2,0,28,2,0,1,11,2,0,259,0,4,1,0,28,2,3,1,6,2,0,260,26,2,0,0,22,0,30,0,6,2,0,260,20,2,2,0,24,0,261,2,22,0,26,0,5,2,0,0,6,2,2,257,0,3,1,0,5,4,6,0,11,4,4,263,28,4,2,2,1,5,4,0,21,4,4,5,28,2,3,1,5,2,8,0,6,3,0,260,28,2,2,4,22,0,11,0,5,7,0,0,6,7,7,257,0,8,1,0,5,9,6,0,11,9,9,263,1,11,9,0,28,9,3,2,11,10,6,258,28,10,2,2,21,9,9,10,28,7,3,1,33,2,0,2,22,0,-13,0,6,2,0,266,26,2,0,0,22,0,30,0,6,2,0,266,20,2,2,0,24,0,261,2,22,0,26,0,5,2,0,0,6,2,2,257,0,3,1,0,5,4,6,0,11,4,4,263,28,4,2,2,1,5,10,0,21,4,4,5,28,2,3,1,5,2,8,0,6,3,0,266,28,2,2,4,22,0,11,0,5,7,0,0,6,7,7,257,0,8,1,0,5,9,6,0,11,9,9,263,1,11,9,0,28,9,3,2,11,10,6,258,28,10,2,2,21,9,9,10,28,7,3,1,33,2,0,2,22,0,-13,0,6,2,0,267,26,2,0,0,22,0,30,0,6,2,0,267,20,2,2,0,24,0,261,2,22,0,26,0,5,2,0,0,6,2,2,257,0,3,1,0,5,4,6,0,11,4,4,263,28,4,2,2,1,5,11,0,21,4,4,5,28,2,3,1,5,2,8,0,6,3,0,267,28,2,2,4,22,0,11,0,5,7,0,0,6,7,7,257,0,8,1,0,5,9,6,0,11,9,9,263,1,11,9,0,28,9,3,2,11,10,6,258,28,10,2,2,21,9,9,10,28,7,3,1,33,2,0,2,22,0,-13,0,30,1,2,0,30,0,1,0],"constants":["table","insert","GetSingleOutputLine","AddDocumentationTags","Functions",0,"APIDocumentation","GetIndentString","ipairs",2,"Events","Tables"],"functions":[],"linePositions":[42,43,43,43,43,43,43,45,45,45,47,47,47,47,47,47,47,48,48,48,48,48,48,48,48,48,49,49,49,49,50,50,50,50,50,50,50,50,50,50,50,49,50,54,54,54,54,54,54,54,55,55,55,55,55,55,55,55,55,56,56,56,56,57,57,57,57,57,57,57,57,57,57,57,56,57,61,61,61,61,61,61,61,62,62,62,62,62,62,62,62,62,63,63,63,63,64,64,64,64,64,64,64,64,64,64,64,63,64,68,69],"locals":[{"varname":"self","startpc":0,"endpc":110},{"varname":"lines","startpc":1,"endpc":110},{"varname":"(for generator)","startpc":29,"endpc":43},{"varname":"(for state)","startpc":29,"endpc":43},{"varname":"(for control)","startpc":29,"endpc":43},{"varname":"i","startpc":30,"endpc":41},{"varname":"functionInfo","startpc":30,"endpc":41},{"varname":"(for generator)","startpc":62,"endpc":76},{"varname":"(for state)","startpc":62,"endpc":76},{"varname":"(for control)","startpc":62,"endpc":76},{"varname":"i","startpc":63,"endpc":74},{"varname":"eventInfo","startpc":63,"endpc":74},{"varname":"(for generator)","startpc":95,"endpc":109},{"varname":"(for state)","startpc":95,"endpc":109},{"varname":"(for control)","startpc":95,"endpc":109},{"varname":"i","startpc":96,"endpc":107},{"varname":"tableInfo","startpc":96,"endpc":107}],"upvalues":[]},{"sourceName":"","lineDefined":71,"lastLineDefined":77,"upvalueCount":0,"paramCount":3,"is_vararg":0,"maxStackSize":7,"instructions":[5,3,0,0,6,3,3,257,0,4,0,0,0,5,1,0,0,6,2,0,28,3,4,2,26,3,0,0,22,0,2,0,2,3,1,0,30,3,2,0,11,3,0,258,28,3,2,2,23,1,1,3,22,0,1,0,2,3,0,1,2,3,1,0,30,3,2,0,30,0,1,0],"constants":["BaseAPIMixin","MatchesName","GetNamespaceName"],"functions":[],"linePositions":[72,72,72,72,72,72,72,72,73,73,76,76,76,76,76,76,76,77],"locals":[{"varname":"self","startpc":0,"endpc":17},{"varname":"name","startpc":0,"endpc":17},{"varname":"parentName","startpc":0,"endpc":17}],"upvalues":[]},{"sourceName":"","lineDefined":79,"lastLineDefined":85,"upvalueCount":0,"paramCount":3,"is_vararg":0,"maxStackSize":7,"instructions":[5,3,0,0,6,3,3,257,0,4,0,0,0,5,1,0,0,6,2,0,28,3,4,2,26,3,0,0,22,0,2,0,2,3,1,0,30,3,2,0,11,3,0,258,28,3,2,2,23,1,1,3,22,0,1,0,2,3,0,1,2,3,1,0,30,3,2,0,30,0,1,0],"constants":["BaseAPIMixin","MatchesNameCaseInsenstive","GetLoweredNamespaceName"],"functions":[],"linePositions":[80,80,80,80,80,80,80,80,81,81,84,84,84,84,84,84,84,85],"locals":[{"varname":"self","startpc":0,"endpc":17},{"varname":"name","startpc":0,"endpc":17},{"varname":"parentName","startpc":0,"endpc":17}],"upvalues":[]},{"sourceName":"","lineDefined":87,"lastLineDefined":108,"upvalueCount":0,"paramCount":2,"is_vararg":0,"maxStackSize":9,"instructions":[11,2,1,256,28,2,2,2,0,1,2,0,10,2,0,3,10,3,0,0,9,2,257,3,10,3,0,0,9,2,258,3,10,3,0,0,9,2,259,3,5,3,4,0,11,3,3,261,6,5,0,262,6,6,2,257,0,7,1,0,28,3,5,1,5,3,4,0,11,3,3,261,6,5,0,263,6,6,2,258,0,7,1,0,28,3,5,1,5,3,4,0,11,3,3,261,6,5,0,264,6,6,2,259,0,7,1,0,28,3,5,1,5,3,9,0,0,4,2,0,28,3,2,4,22,0,4,0,20,8,7,0,24,0,266,8,22,0,1,0,30,2,2,0,33,3,0,2,22,0,-6,0,3,3,3,0,30,3,2,0,30,0,1,0],"constants":["lower","tables","functions","events","APIDocumentationMixin","AddAllMatches","Tables","Functions","Events","pairs",0],"functions":[],"linePositions":[88,88,88,90,91,91,92,92,93,93,96,96,96,96,96,96,97,97,97,97,97,97,98,98,98,98,98,98,101,101,101,101,102,102,102,103,101,104,107,107,108],"locals":[{"varname":"self","startpc":0,"endpc":40},{"varname":"apiToSearchFor","startpc":0,"endpc":40},{"varname":"matches","startpc":10,"endpc":40},{"varname":"(for generator)","startpc":31,"endpc":38},{"varname":"(for state)","startpc":31,"endpc":38},{"varname":"(for control)","startpc":31,"endpc":38},{"varname":"name","startpc":32,"endpc":36},{"varname":"subTable","startpc":32,"endpc":36}],"upvalues":[]},{"sourceName":"","lineDefined":110,"lastLineDefined":116,"upvalueCount":0,"paramCount":2,"is_vararg":0,"maxStackSize":10,"instructions":[26,0,0,0,22,0,11,0,5,2,0,0,0,3,0,0,28,2,2,4,22,0,5,0,5,7,1,0,6,7,7,258,0,8,1,0,0,9,6,0,28,7,3,1,33,2,0,2,22,0,-7,0,30,0,1,0],"constants":["ipairs","table","insert"],"functions":[],"linePositions":[111,111,112,112,112,112,113,113,113,113,113,112,113,116],"locals":[{"varname":"apiContainer","startpc":0,"endpc":13},{"varname":"matchesContainer","startpc":0,"endpc":13},{"varname":"(for generator)","startpc":5,"endpc":13},{"varname":"(for state)","startpc":5,"endpc":13},{"varname":"(for control)","startpc":5,"endpc":13},{"varname":"i","startpc":6,"endpc":11},{"varname":"apiInfo","startpc":6,"endpc":11}],"upvalues":[]},{"sourceName":"","lineDefined":118,"lastLineDefined":130,"upvalueCount":1,"paramCount":1,"is_vararg":0,"maxStackSize":5,"instructions":[10,1,0,3,10,2,0,0,9,1,256,2,10,2,0,0,9,1,257,2,10,2,0,0,9,1,258,2,4,2,0,0,6,3,0,259,6,4,1,256,28,2,3,1,4,2,0,0,6,3,0,260,6,4,1,257,28,2,3,1,4,2,0,0,6,3,0,261,6,4,1,258,28,2,3,1,30,1,2,0,30,0,1,0],"constants":["tables","functions","events","Tables","Functions","Events"],"functions":[],"linePositions":[119,120,120,121,121,122,122,125,125,125,125,126,126,126,126,127,127,127,127,129,130],"locals":[{"varname":"self","startpc":0,"endpc":20},{"varname":"allAPI","startpc":7,"endpc":20}],"upvalues":["AddAll"]},{"sourceName":"","lineDefined":132,"lastLineDefined":134,"upvalueCount":0,"paramCount":1,"is_vararg":0,"maxStackSize":2,"instructions":[6,1,0,256,26,1,0,0,22,0,4,0,6,1,0,256,20,1,1,0,26,1,0,1,22,0,1,0,1,1,1,0,30,1,2,0,30,0,1,0],"constants":["Tables",0],"functions":[],"linePositions":[133,133,133,133,133,133,133,133,133,134],"locals":[{"varname":"self","startpc":0,"endpc":9}],"upvalues":[]},{"sourceName":"","lineDefined":136,"lastLineDefined":138,"upvalueCount":0,"paramCount":1,"is_vararg":0,"maxStackSize":2,"instructions":[6,1,0,256,26,1,0,0,22,0,4,0,6,1,0,256,20,1,1,0,26,1,0,1,22,0,1,0,1,1,1,0,30,1,2,0,30,0,1,0],"constants":["Functions",0],"functions":[],"linePositions":[137,137,137,137,137,137,137,137,137,138],"locals":[{"varname":"self","startpc":0,"endpc":9}],"upvalues":[]},{"sourceName":"","lineDefined":140,"lastLineDefined":142,"upvalueCount":0,"paramCount":1,"is_vararg":0,"maxStackSize":2,"instructions":[6,1,0,256,26,1,0,0,22,0,4,0,6,1,0,256,20,1,1,0,26,1,0,1,22,0,1,0,1,1,1,0,30,1,2,0,30,0,1,0],"constants":["Events",0],"functions":[],"linePositions":[141,141,141,141,141,141,141,141,141,142],"locals":[{"varname":"self","startpc":0,"endpc":9}],"upvalues":[]}],"linePositions":[1,1,1,1,3,5,3,7,9,7,11,13,11,15,20,15,22,32,22,34,39,34,41,69,41,71,77,71,79,85,79,87,108,87,116,118,130,130,118,132,134,132,136,138,136,140,142,140,142],"locals":[{"varname":"AddAll","startpc":35,"endpc":48}],"upvalues":[],"sourcePath":"Blizzard_APIDocumentation\\SystemsAPIMixin.lua"}